moped/__init__.py
moped/core/__init__.py
moped/core/compound.py
moped/core/constants.py
moped/core/kinetic_data.py
moped/core/model.py
moped/core/monomer.py
moped/core/reaction.py
moped/py.typed
moped/topological/__init__.py
moped/topological/blast.py
moped/topological/gapfilling.py
moped/topological/scope.py
moped/topological/treesearch.py
moped/utils/__init__.py
moped/utils/comparison.py
moped/utils/sbml.py
moped/utils/serialize.py
moped-1.13.94.dist-info/LICENSE
moped-1.13.94.dist-info/WHEEL
moped-1.13.94.dist-info/METADATA
moped-1.13.94.dist-info/RECORD
