Metadata-Version: 2.1
Name: moped
Version: 1.13.94
Summary: Stoichiometric metabolic modelling
Home-page: https://gitlab.com/marvin.vanaalst/moped
License: GPL-3.0-or-later
Keywords: modelling,stoichiometric,metacyc,blast
Author: Marvin van Aalst
Author-email: marvin.vanaalst@gmail.com
Maintainer: Marvin van Aalst
Maintainer-email: marvin.vanaalst@gmail.com
Requires-Python: >=3.8,<4.0
Classifier: Development Status :: 5 - Production/Stable
Classifier: Environment :: Console
Classifier: Intended Audience :: Developers
Classifier: Intended Audience :: Science/Research
Classifier: License :: OSI Approved :: GNU General Public License v3 or later (GPLv3+)
Classifier: Operating System :: MacOS
Classifier: Operating System :: Microsoft :: Windows
Classifier: Operating System :: OS Independent
Classifier: Operating System :: POSIX
Classifier: Operating System :: Unix
Classifier: Programming Language :: Python :: 3
Classifier: Programming Language :: Python :: 3.8
Classifier: Programming Language :: Python :: 3.9
Classifier: Programming Language :: Python :: 3.10
Classifier: Programming Language :: Python :: 3.11
Classifier: Programming Language :: Python :: 3
Classifier: Programming Language :: Python :: 3.8
Classifier: Programming Language :: Python :: 3.9
Classifier: Topic :: Scientific/Engineering
Classifier: Topic :: Software Development
Requires-Dist: Meneco (>=2.0.2,<3.0.0)
Requires-Dist: PyYAML (>=6.0,<7.0)
Requires-Dist: cobra (>=0.26.0,<0.27.0)
Requires-Dist: cycparser (>=1.2.1,<2.0.0)
Requires-Dist: gitchangelog (>=3.0.4,<4.0.0)
Requires-Dist: modelbase (>=1.9.2,<2.0.0)
Requires-Dist: numpy (>=1.22.4,<1.24.0)
Requires-Dist: pandas (>=1.4.2,<2.0.0)
Requires-Dist: pipdeptree (>=2.2.1,<3.0.0)
Requires-Dist: python-libsbml (>=5.19.5,<6.0.0)
Requires-Dist: tqdm (>=4.46.0,<5.0.0)
Project-URL: Documentation, https://moped.readthedocs.io/en/latest/
Project-URL: Repository, https://gitlab.com/marvin.vanaalst/moped
